README.txt
setup.cfg
setup.py
docs/HISTORY.txt
infrae/__init__.py
infrae.subversion.egg-info/PKG-INFO
infrae.subversion.egg-info/SOURCES.txt
infrae.subversion.egg-info/dependency_links.txt
infrae.subversion.egg-info/entry_points.txt
infrae.subversion.egg-info/namespace_packages.txt
infrae.subversion.egg-info/requires.txt
infrae.subversion.egg-info/top_level.txt
infrae/subversion/Common.py
infrae/subversion/Native.py
infrae/subversion/Py.py
infrae/subversion/__init__.py
infrae/subversion/tests/EXPORT.txt
infrae/subversion/tests/IMPL.txt
infrae/subversion/tests/__init__.py
infrae/subversion/tests/test_impl.py