Metadata-Version: 1.0
Name: infrae.subversion
Version: 1.2
Summary: Buildout recipe for checking out from subversion
Home-page: https://svn.infrae.com/buildout/infrae.buildout/trunk/
Author: Eric Casteleijn, Guido Wesdorp, Daniel Nouri and Sylvain Viollon
Author-email: info@infrae.com
License: ZPL 2.1
Keywords: subversion buildout
Platform: UNKNOWN
Classifier: Framework :: Buildout
Classifier: License :: OSI Approved :: Zope Public License
Classifier: Topic :: Software Development :: Version Control
